README.txt
setup.py
docs/HISTORY.txt
docs/INSTALL.txt
docs/LICENSE.GPL
docs/LICENSE.txt
redturtle/__init__.py
redturtle.bent.egg-info/PKG-INFO
redturtle.bent.egg-info/SOURCES.txt
redturtle.bent.egg-info/dependency_links.txt
redturtle.bent.egg-info/entry_points.txt
redturtle.bent.egg-info/namespace_packages.txt
redturtle.bent.egg-info/not-zip-safe
redturtle.bent.egg-info/requires.txt
redturtle.bent.egg-info/top_level.txt
redturtle/bent/__init__.py
redturtle/bent/plugins.py