Metadata-Version: 1.0
Name: redturtle.bent
Version: 0.0.2
Summary: RedTurtle plugins for mr.bent
Home-page: http://www.redturtle.net
Author: Andrew Mleczko
Author-email: andrew.mleczko@redturtle.net
License: GPL
Platform: UNKNOWN
Classifier: Framework :: Plone
Classifier: Programming Language :: Python
Classifier: Topic :: Software Development :: Libraries :: Python Modules
